muniverse/__init__.py
muniverse/actions.py
muniverse/env.py
muniverse/errors.py
muniverse/handle.py
muniverse/proto.py
muniverse/spec.py
muniverse-0.1.1.dist-info/DESCRIPTION.rst
muniverse-0.1.1.dist-info/METADATA
muniverse-0.1.1.dist-info/RECORD
muniverse-0.1.1.dist-info/WHEEL
muniverse-0.1.1.dist-info/metadata.json
muniverse-0.1.1.dist-info/top_level.txt
