Metadata-Version: 2.0
Name: muniverse
Version: 0.1.1
Summary: An API for controlling muniverse environments.
Home-page: https://github.com/unixpickle/muniverse
Author: Alex Nichol
Author-email: unixpickle@gmail.com
License: BSD
Keywords: ai reinforcement learning
Platform: UNKNOWN
Classifier: Development Status :: 4 - Beta
Classifier: Intended Audience :: Developers
Classifier: License :: OSI Approved :: BSD License
Classifier: Programming Language :: Python :: 2
Classifier: Programming Language :: Python :: 2.7
Classifier: Programming Language :: Python :: 3
Classifier: Programming Language :: Python :: 3.3
Classifier: Programming Language :: Python :: 3.4
Classifier: Programming Language :: Python :: 3.5
Requires-Dist: bson
Requires-Dist: numpy
